{"areacd":"E07000208","areanm":"Epsom and Ewell","parentcd":"E12000008","parentnm.x":"South East","country":"N","region":"N","localauthority":"Y","countrycd":"E92000001","similar":"S12000042|E07000092|E07000135|E06000058|N09000003","parentnm.y":"South East","employment_rate_2012":78.5,"employment_rate_2013":71.1,"employment_rate_2014":83.4,"employment_rate_2015":80.1,"employment_rate_2016":84.7,"employment_rate_2017":73,"employment_rate_2018":80.8,"employment_rate_2019":82.8,"employment_rate_2020":86.6,"employment_rate_2021":80.5,"employment_rate_2022":76.4,"parentnm.x.1":"South East","female_life_expectancy_2003":83.8,"female_life_expectancy_2004":84.1,"female_life_expectancy_2005":84.4,"female_life_expectancy_2006":84,"female_life_expectancy_2007":84.1,"female_life_expectancy_2008":84,"female_life_expectancy_2009":85,"female_life_expectancy_2010":85.3,"female_life_expectancy_2011":85.5,"female_life_expectancy_2012":85.2,"female_life_expectancy_2013":85.3,"female_life_expectancy_2014":85.5,"female_life_expectancy_2015":85.5,"female_life_expectancy_2016":85.3,"female_life_expectancy_2017":85.8,"female_life_expectancy_2018":86.1,"parentnm.y.1":"South East","gdhi_1997":15317,"gdhi_1998":16086,"gdhi_1999":16720,"gdhi_2000":17586,"gdhi_2001":17974,"gdhi_2002":18396,"gdhi_2003":18470,"gdhi_2004":18920,"gdhi_2005":19970,"gdhi_2006":21435,"gdhi_2007":22166,"gdhi_2008":22195,"gdhi_2009":22081,"gdhi_2010":22201,"gdhi_2011":22602,"gdhi_2012":23680,"gdhi_2013":24487,"gdhi_2014":24849,"gdhi_2015":26933,"gdhi_2016":27043,"gdhi_2017":27634,"gdhi_2018":28348,"gdhi_2019":28184,"gdhi_2020":27999,"parentnm.x.2":"South East","gva_hour_2004":30,"gva_hour_2005":30.1,"gva_hour_2006":32.3,"gva_hour_2007":33.3,"gva_hour_2008":33.5,"gva_hour_2009":32.4,"gva_hour_2010":31.9,"gva_hour_2011":31.4,"gva_hour_2012":31.5,"gva_hour_2013":31.3,"gva_hour_2014":31.5,"gva_hour_2015":31.8,"gva_hour_2016":32.5,"gva_hour_2017":33.4,"gva_hour_2018":34.1,"gva_hour_2019":34.5,"gva_hour_2020":34.5,"parentnm.y.2":"South East","internet_access_2022":100,"parentnm.x.3":"South East","median_age_2001":40.12,"median_age_2002":40.17,"median_age_2003":40.18,"median_age_2004":40.35,"median_age_2005":40.48,"median_age_2006":40.53,"median_age_2007":40.44,"median_age_2008":40.53,"median_age_2009":40.76,"median_age_2010":40.81,"median_age_2011":40.87,"median_age_2012":41.02,"median_age_2013":41.05,"median_age_2014":41.01,"median_age_2015":41.17,"median_age_2016":41.24,"median_age_2017":41.37,"median_age_2018":41.48,"median_age_2019":41.53,"median_age_2020":41.69,"parentnm.y.3":"South East","no_qualifications_rate_2013":7,"no_qualifications_rate_2014":3.2,"no_qualifications_rate_2015":4,"no_qualifications_rate_2016":2.9,"no_qualifications_rate_2017":4.5,"no_qualifications_rate_2018":2.7,"no_qualifications_rate_2019":4.1,"no_qualifications_rate_2020":7,"parentnm.x.4":"South East","population_2001":67077,"population_2002":67554,"population_2003":67738,"population_2004":68386,"population_2005":69172,"population_2006":70028,"population_2007":71337,"population_2008":72514,"population_2009":73106,"population_2010":74278,"population_2011":75191,"population_2012":75839,"population_2013":76906,"population_2014":77988,"population_2015":78459,"population_2016":78999,"population_2017":79451,"population_2018":79928,"population_2019":80627,"population_2020":81003,"parentnm.y.4":"South East","population_density_2001":1968.2565,"population_density_2002":1982.2532,"population_density_2003":1987.6524,"population_density_2004":2006.6668,"population_density_2005":2029.7306,"population_density_2006":2054.8484,"population_density_2007":2093.2587,"population_density_2008":2127.7957,"population_density_2009":2145.1669,"population_density_2010":2179.5572,"population_density_2011":2206.3475,"population_density_2012":2225.3619,"population_density_2013":2256.6712,"population_density_2014":2288.4206,"population_density_2015":2302.2412,"population_density_2016":2318.0866,"population_density_2017":2331.3497,"population_density_2018":2345.3465,"population_density_2019":2365.8574,"population_density_2020":2376.8904,"parentnm":"South East","unemployment_rate_2013":6.2,"unemployment_rate_2014":2.7,"unemployment_rate_2017":6,"unemployment_rate_2018":5.2,"unemployment_rate_2019":4.4,"unemployment_rate_2021":6.8,"unemployment_rate_2022":8.4}
