{"areacd":"E07000134","areanm":"North West Leicestershire","parentcd":"E12000004","parentnm.x":"East Midlands","country":"N","region":"N","localauthority":"Y","countrycd":"E92000001","similar":"E10000024|E07000108|E10000014|E07000132|E07000072","parentnm.y":"East Midlands","employment_rate_2012":73.3,"employment_rate_2013":70.5,"employment_rate_2014":74.2,"employment_rate_2015":81.5,"employment_rate_2016":77.1,"employment_rate_2017":84.5,"employment_rate_2018":71.9,"employment_rate_2019":71.5,"employment_rate_2020":69.8,"employment_rate_2021":78.4,"employment_rate_2022":76.8,"parentnm.x.1":"East Midlands","female_life_expectancy_2003":80.4,"female_life_expectancy_2004":80.6,"female_life_expectancy_2005":80.6,"female_life_expectancy_2006":81.3,"female_life_expectancy_2007":81.2,"female_life_expectancy_2008":81.8,"female_life_expectancy_2009":81.9,"female_life_expectancy_2010":82.1,"female_life_expectancy_2011":82.6,"female_life_expectancy_2012":82.8,"female_life_expectancy_2013":83.4,"female_life_expectancy_2014":83.2,"female_life_expectancy_2015":83.3,"female_life_expectancy_2016":82.9,"female_life_expectancy_2017":83,"female_life_expectancy_2018":83.2,"parentnm.y.1":"East Midlands","gdhi_1997":10802,"gdhi_1998":10976,"gdhi_1999":11511,"gdhi_2000":11971,"gdhi_2001":12351,"gdhi_2002":12625,"gdhi_2003":13171,"gdhi_2004":13595,"gdhi_2005":13973,"gdhi_2006":14344,"gdhi_2007":15059,"gdhi_2008":15146,"gdhi_2009":15440,"gdhi_2010":15674,"gdhi_2011":16040,"gdhi_2012":16555,"gdhi_2013":17076,"gdhi_2014":17366,"gdhi_2015":18075,"gdhi_2016":17884,"gdhi_2017":18672,"gdhi_2018":18958,"gdhi_2019":19608,"gdhi_2020":19831,"parentnm.x.2":"East Midlands","gva_hour_2004":25.7,"gva_hour_2005":25.6,"gva_hour_2006":26.4,"gva_hour_2007":27,"gva_hour_2008":27.7,"gva_hour_2009":28.3,"gva_hour_2010":28.6,"gva_hour_2011":28.9,"gva_hour_2012":29.6,"gva_hour_2013":30.8,"gva_hour_2014":32,"gva_hour_2015":32.5,"gva_hour_2016":32.9,"gva_hour_2017":33.2,"gva_hour_2018":33.6,"gva_hour_2019":33.8,"gva_hour_2020":33.9,"parentnm.y.2":"East Midlands","internet_access_2022":99.99,"parentnm.x.3":"East Midlands","median_age_2001":39.71,"median_age_2002":39.9,"median_age_2003":40.11,"median_age_2004":40.28,"median_age_2005":40.51,"median_age_2006":40.79,"median_age_2007":41.02,"median_age_2008":41.34,"median_age_2009":41.74,"median_age_2010":42.09,"median_age_2011":42.46,"median_age_2012":42.79,"median_age_2013":43.03,"median_age_2014":43.29,"median_age_2015":43.53,"median_age_2016":43.74,"median_age_2017":43.89,"median_age_2018":43.85,"median_age_2019":43.9,"median_age_2020":43.9,"parentnm.y.3":"East Midlands","no_qualifications_rate_2012":8.1,"no_qualifications_rate_2013":10.2,"no_qualifications_rate_2014":9.4,"no_qualifications_rate_2015":8.5,"no_qualifications_rate_2016":4.8,"no_qualifications_rate_2017":5.8,"no_qualifications_rate_2018":8.1,"no_qualifications_rate_2019":7.1,"no_qualifications_rate_2020":6.3,"no_qualifications_rate_2021":5,"parentnm.x.4":"East Midlands","population_2001":85678,"population_2002":86842,"population_2003":87794,"population_2004":88845,"population_2005":89623,"population_2006":90406,"population_2007":91476,"population_2008":92283,"population_2009":92728,"population_2010":93165,"population_2011":93670,"population_2012":93985,"population_2013":94716,"population_2014":95731,"population_2015":97098,"population_2016":98436,"population_2017":100109,"population_2018":102126,"population_2019":103611,"population_2020":104809,"parentnm.y.4":"East Midlands","population_density_2001":306.729,"population_density_2002":310.8962,"population_density_2003":314.3043,"population_density_2004":318.0669,"population_density_2005":320.8522,"population_density_2006":323.6553,"population_density_2007":327.486,"population_density_2008":330.375,"population_density_2009":331.9682,"population_density_2010":333.5326,"population_density_2011":335.3405,"population_density_2012":336.4682,"population_density_2013":339.0852,"population_density_2014":342.719,"population_density_2015":347.6128,"population_density_2016":352.4029,"population_density_2017":358.3923,"population_density_2018":365.6132,"population_density_2019":370.9295,"population_density_2020":375.2184,"parentnm":"East Midlands","unemployment_rate_2012":4.5,"unemployment_rate_2013":6.9,"unemployment_rate_2014":3.2,"unemployment_rate_2015":3.4,"unemployment_rate_2016":4.1,"unemployment_rate_2017":2.6,"unemployment_rate_2018":7.4,"unemployment_rate_2019":5.8,"unemployment_rate_2020":6.1,"unemployment_rate_2021":4.5,"unemployment_rate_2022":2.5}
