{"areacd":"E07000039","areanm":"South Derbyshire","parentcd":"E12000004","parentnm.x":"East Midlands","country":"N","region":"N","localauthority":"Y","countrycd":"E92000001","similar":"E07000127|E10000011|W06000012|E12000006|E07000111","parentnm.y":"East Midlands","employment_rate_2012":71.4,"employment_rate_2013":79.1,"employment_rate_2014":81.1,"employment_rate_2015":73.8,"employment_rate_2016":80,"employment_rate_2017":79.2,"employment_rate_2018":82.4,"employment_rate_2019":87.8,"employment_rate_2020":78.4,"employment_rate_2021":80.8,"employment_rate_2022":76.2,"parentnm.x.1":"East Midlands","female_life_expectancy_2003":80.2,"female_life_expectancy_2004":80.6,"female_life_expectancy_2005":80.9,"female_life_expectancy_2006":81.6,"female_life_expectancy_2007":81.9,"female_life_expectancy_2008":81.8,"female_life_expectancy_2009":81.6,"female_life_expectancy_2010":82.2,"female_life_expectancy_2011":83,"female_life_expectancy_2012":83.2,"female_life_expectancy_2013":82.7,"female_life_expectancy_2014":83,"female_life_expectancy_2015":82.7,"female_life_expectancy_2016":83,"female_life_expectancy_2017":82.5,"female_life_expectancy_2018":82.9,"parentnm.y.1":"East Midlands","gdhi_1997":10521,"gdhi_1998":10685,"gdhi_1999":11507,"gdhi_2000":11957,"gdhi_2001":12247,"gdhi_2002":12481,"gdhi_2003":13289,"gdhi_2004":13678,"gdhi_2005":14082,"gdhi_2006":14464,"gdhi_2007":15069,"gdhi_2008":15203,"gdhi_2009":15273,"gdhi_2010":15219,"gdhi_2011":15783,"gdhi_2012":16307,"gdhi_2013":16975,"gdhi_2014":17188,"gdhi_2015":18315,"gdhi_2016":18212,"gdhi_2017":18413,"gdhi_2018":19181,"gdhi_2019":19653,"gdhi_2020":19399,"parentnm.x.2":"East Midlands","gva_hour_2004":31.9,"gva_hour_2005":31.6,"gva_hour_2006":32.9,"gva_hour_2007":34,"gva_hour_2008":35.3,"gva_hour_2009":36.4,"gva_hour_2010":36.7,"gva_hour_2011":37.4,"gva_hour_2012":39.1,"gva_hour_2013":42.5,"gva_hour_2014":46.3,"gva_hour_2015":48.7,"gva_hour_2016":50.1,"gva_hour_2017":50.8,"gva_hour_2018":53.3,"gva_hour_2019":56.3,"gva_hour_2020":58.7,"parentnm.y.2":"East Midlands","internet_access_2022":100,"parentnm.x.3":"East Midlands","median_age_2001":38.43,"median_age_2002":38.6,"median_age_2003":38.77,"median_age_2004":38.97,"median_age_2005":39.2,"median_age_2006":39.37,"median_age_2007":39.55,"median_age_2008":39.81,"median_age_2009":40.1,"median_age_2010":40.38,"median_age_2011":40.79,"median_age_2012":41.22,"median_age_2013":41.53,"median_age_2014":41.83,"median_age_2015":42.09,"median_age_2016":42.24,"median_age_2017":42.23,"median_age_2018":42.22,"median_age_2019":42.05,"median_age_2020":41.94,"parentnm.y.3":"East Midlands","no_qualifications_rate_2012":10.1,"no_qualifications_rate_2013":10,"no_qualifications_rate_2014":4.6,"no_qualifications_rate_2015":2.9,"no_qualifications_rate_2016":3.3,"no_qualifications_rate_2017":8.6,"no_qualifications_rate_2018":5.7,"no_qualifications_rate_2019":1.9,"no_qualifications_rate_2020":5.1,"no_qualifications_rate_2021":4.6,"parentnm.x.4":"East Midlands","population_2001":81738,"population_2002":83480,"population_2003":85312,"population_2004":86506,"population_2005":87832,"population_2006":89295,"population_2007":90655,"population_2008":92023,"population_2009":93015,"population_2010":94095,"population_2011":94915,"population_2012":95934,"population_2013":97111,"population_2014":98395,"population_2015":99345,"population_2016":100421,"population_2017":102385,"population_2018":104493,"population_2019":107261,"population_2020":109516,"parentnm.y.4":"East Midlands","population_density_2001":241.7376,"population_density_2002":246.8896,"population_density_2003":252.3076,"population_density_2004":255.8389,"population_density_2005":259.7605,"population_density_2006":264.0872,"population_density_2007":268.1094,"population_density_2008":272.1552,"population_density_2009":275.089,"population_density_2010":278.2831,"population_density_2011":280.7082,"population_density_2012":283.7219,"population_density_2013":287.2028,"population_density_2014":291.0002,"population_density_2015":293.8098,"population_density_2016":296.992,"population_density_2017":302.8005,"population_density_2018":309.0349,"population_density_2019":317.2211,"population_density_2020":323.8902,"parentnm":"East Midlands","unemployment_rate_2012":7.2,"unemployment_rate_2015":5.5,"unemployment_rate_2016":4.1,"unemployment_rate_2018":4.5,"unemployment_rate_2019":2.2,"unemployment_rate_2020":4.5,"unemployment_rate_2021":5.2,"unemployment_rate_2022":6.1}
