{"areacd":"E08000022","areanm":"North Tyneside","parentcd":"E12000001","parentnm.x":"North East","country":"N","region":"N","localauthority":"Y","countrycd":"E92000001","similar":"E08000021|W06000015|E06000002|E09000017|E08000006","parentnm.y":"North East","employment_rate_2012":69,"employment_rate_2013":68.7,"employment_rate_2014":73.6,"employment_rate_2015":75.9,"employment_rate_2016":76.4,"employment_rate_2017":76,"employment_rate_2018":74.2,"employment_rate_2019":78,"employment_rate_2020":76.7,"employment_rate_2021":71.9,"employment_rate_2022":74.9,"parentnm.x.1":"North East","female_life_expectancy_2003":80,"female_life_expectancy_2004":80,"female_life_expectancy_2005":80.4,"female_life_expectancy_2006":80.6,"female_life_expectancy_2007":80.9,"female_life_expectancy_2008":80.6,"female_life_expectancy_2009":81,"female_life_expectancy_2010":81.2,"female_life_expectancy_2011":81.6,"female_life_expectancy_2012":81.9,"female_life_expectancy_2013":82.4,"female_life_expectancy_2014":82.6,"female_life_expectancy_2015":82.4,"female_life_expectancy_2016":82.5,"female_life_expectancy_2017":82.1,"female_life_expectancy_2018":82.1,"parentnm.y.1":"North East","gdhi_1997":9907,"gdhi_1998":10103,"gdhi_1999":10275,"gdhi_2000":10718,"gdhi_2001":11052,"gdhi_2002":11239,"gdhi_2003":11526,"gdhi_2004":12120,"gdhi_2005":12166,"gdhi_2006":12547,"gdhi_2007":12870,"gdhi_2008":12956,"gdhi_2009":13646,"gdhi_2010":14037,"gdhi_2011":14229,"gdhi_2012":15048,"gdhi_2013":15320,"gdhi_2014":15598,"gdhi_2015":16454,"gdhi_2016":16524,"gdhi_2017":16962,"gdhi_2018":17647,"gdhi_2019":18229,"gdhi_2020":18531,"parentnm.x.2":"North East","gva_hour_2004":26.6,"gva_hour_2005":26.7,"gva_hour_2006":27.1,"gva_hour_2007":27.7,"gva_hour_2008":28.1,"gva_hour_2009":28.4,"gva_hour_2010":28.5,"gva_hour_2011":28.9,"gva_hour_2012":29.1,"gva_hour_2013":29.1,"gva_hour_2014":29,"gva_hour_2015":29.5,"gva_hour_2016":30.2,"gva_hour_2017":31.1,"gva_hour_2018":32.4,"gva_hour_2019":33.9,"gva_hour_2020":35.1,"parentnm.y.2":"North East","internet_access_2022":100,"parentnm.x.3":"North East","median_age_2001":40.12,"median_age_2002":40.28,"median_age_2003":40.51,"median_age_2004":40.73,"median_age_2005":40.94,"median_age_2006":41.08,"median_age_2007":41.23,"median_age_2008":41.31,"median_age_2009":41.49,"median_age_2010":41.7,"median_age_2011":41.9,"median_age_2012":42.24,"median_age_2013":42.44,"median_age_2014":42.74,"median_age_2015":43.05,"median_age_2016":43.23,"median_age_2017":43.35,"median_age_2018":43.38,"median_age_2019":43.33,"median_age_2020":43.3,"parentnm.y.3":"North East","no_qualifications_rate_2012":9.1,"no_qualifications_rate_2013":10.6,"no_qualifications_rate_2014":6.2,"no_qualifications_rate_2015":7.7,"no_qualifications_rate_2016":7.9,"no_qualifications_rate_2017":5.8,"no_qualifications_rate_2018":7.2,"no_qualifications_rate_2019":5.5,"no_qualifications_rate_2020":4.8,"no_qualifications_rate_2021":7.3,"parentnm.x.4":"North East","population_2001":192003,"population_2002":192739,"population_2003":193037,"population_2004":193195,"population_2005":194120,"population_2006":195365,"population_2007":196470,"population_2008":197964,"population_2009":199017,"population_2010":200164,"population_2011":201206,"population_2012":201444,"population_2013":202167,"population_2014":202857,"population_2015":202725,"population_2016":203575,"population_2017":204473,"population_2018":205985,"population_2019":207913,"population_2020":208871,"parentnm.y.4":"North East","population_density_2001":2332.5708,"population_density_2002":2341.5122,"population_density_2003":2345.1325,"population_density_2004":2347.052,"population_density_2005":2358.2894,"population_density_2006":2373.4145,"population_density_2007":2386.8387,"population_density_2008":2404.9887,"population_density_2009":2417.7812,"population_density_2010":2431.7157,"population_density_2011":2444.3745,"population_density_2012":2447.2659,"population_density_2013":2456.0493,"population_density_2014":2464.4319,"population_density_2015":2462.8283,"population_density_2016":2473.1546,"population_density_2017":2484.0641,"population_density_2018":2502.4328,"population_density_2019":2525.8553,"population_density_2020":2537.4937,"parentnm":"North East","unemployment_rate_2012":10.2,"unemployment_rate_2013":7.9,"unemployment_rate_2014":5.9,"unemployment_rate_2015":5.7,"unemployment_rate_2016":5,"unemployment_rate_2017":6.1,"unemployment_rate_2018":4.4,"unemployment_rate_2019":2.9,"unemployment_rate_2020":5.3,"unemployment_rate_2021":7,"unemployment_rate_2022":5}
