{"areacd":"S12000020","areanm":"Moray","parentcd":"S92000003","parentnm.x":"Scotland","country":"N","region":"N","localauthority":"Y","countrycd":"S92000003","similar":"S12000041|S12000030|E07000047|E07000163|W06000002","parentnm.y":"Scotland","employment_rate_2012":77.6,"employment_rate_2013":78.8,"employment_rate_2014":77.1,"employment_rate_2015":73.4,"employment_rate_2016":75.5,"employment_rate_2017":74.5,"employment_rate_2018":72.8,"employment_rate_2019":75,"employment_rate_2020":75.1,"employment_rate_2021":72.8,"employment_rate_2022":76.6,"parentnm.x.1":"Scotland","female_life_expectancy_2003":80.2,"female_life_expectancy_2004":80.2,"female_life_expectancy_2005":80.2,"female_life_expectancy_2006":80,"female_life_expectancy_2007":80.4,"female_life_expectancy_2008":80.6,"female_life_expectancy_2009":81.2,"female_life_expectancy_2010":81.5,"female_life_expectancy_2011":81.8,"female_life_expectancy_2012":81.7,"female_life_expectancy_2013":81.6,"female_life_expectancy_2014":81.7,"female_life_expectancy_2015":81.7,"female_life_expectancy_2016":82.1,"female_life_expectancy_2017":81.9,"female_life_expectancy_2018":81.7,"parentnm.y.1":"Scotland","gdhi_1997":7866,"gdhi_1998":8046,"gdhi_1999":8368,"gdhi_2000":8730,"gdhi_2001":9117,"gdhi_2002":9397,"gdhi_2003":9501,"gdhi_2004":9770,"gdhi_2005":10030,"gdhi_2006":11185,"gdhi_2007":12193,"gdhi_2008":14331,"gdhi_2009":14398,"gdhi_2010":14685,"gdhi_2011":14579,"gdhi_2012":15368,"gdhi_2013":15781,"gdhi_2014":16233,"gdhi_2015":16867,"gdhi_2016":16872,"gdhi_2017":17497,"gdhi_2018":18277,"gdhi_2019":18774,"gdhi_2020":18827,"parentnm.x.2":"Scotland","gva_hour_2004":23.3,"gva_hour_2005":23.2,"gva_hour_2006":23.8,"gva_hour_2007":24.8,"gva_hour_2008":26.1,"gva_hour_2009":27.8,"gva_hour_2010":29.1,"gva_hour_2011":30,"gva_hour_2012":30.4,"gva_hour_2013":30.7,"gva_hour_2014":30.8,"gva_hour_2015":31,"gva_hour_2016":31.2,"gva_hour_2017":31.9,"gva_hour_2018":33.5,"gva_hour_2019":35.3,"gva_hour_2020":36.6,"parentnm.y.2":"Scotland","internet_access_2022":89.6,"parentnm.x.3":"Scotland","median_age_2001":38.83,"median_age_2002":39.44,"median_age_2003":39.72,"median_age_2004":40.22,"median_age_2005":40.63,"median_age_2006":41.02,"median_age_2007":41.42,"median_age_2008":41.73,"median_age_2009":42.07,"median_age_2010":42.38,"median_age_2011":42.84,"median_age_2012":43.36,"median_age_2013":43.46,"median_age_2014":43.86,"median_age_2015":44.07,"median_age_2016":44.27,"median_age_2017":44.74,"median_age_2018":45.17,"median_age_2019":45.35,"median_age_2020":45.66,"parentnm.y.3":"Scotland","no_qualifications_rate_2012":8.6,"no_qualifications_rate_2013":7.2,"no_qualifications_rate_2014":8.5,"no_qualifications_rate_2015":11.6,"no_qualifications_rate_2016":10,"no_qualifications_rate_2017":10.2,"no_qualifications_rate_2018":8.2,"no_qualifications_rate_2019":9.1,"no_qualifications_rate_2020":7.4,"no_qualifications_rate_2021":5.2,"parentnm.x.4":"Scotland","population_2001":87000,"population_2002":87690,"population_2003":88830,"population_2004":89380,"population_2005":90100,"population_2006":90780,"population_2007":91440,"population_2008":92830,"population_2009":93170,"population_2010":93690,"population_2011":93470,"population_2012":92930,"population_2013":94360,"population_2014":94770,"population_2015":95510,"population_2016":96070,"population_2017":95780,"population_2018":95520,"population_2019":95820,"population_2020":95710,"parentnm.y.4":"Scotland","population_density_2001":38.8817,"population_density_2002":39.1901,"population_density_2003":39.6996,"population_density_2004":39.9454,"population_density_2005":40.2672,"population_density_2006":40.5711,"population_density_2007":40.866,"population_density_2008":41.4873,"population_density_2009":41.6392,"population_density_2010":41.8716,"population_density_2011":41.7733,"population_density_2012":41.532,"population_density_2013":42.171,"population_density_2014":42.3543,"population_density_2015":42.685,"population_density_2016":42.9353,"population_density_2017":42.8057,"population_density_2018":42.6895,"population_density_2019":42.8235,"population_density_2020":42.7744,"parentnm":"Scotland","unemployment_rate_2012":4.3,"unemployment_rate_2013":5,"unemployment_rate_2014":5.1,"unemployment_rate_2015":4.1,"unemployment_rate_2016":4.6,"unemployment_rate_2017":5.2,"unemployment_rate_2018":5.3,"unemployment_rate_2019":3.7,"unemployment_rate_2020":3.4,"unemployment_rate_2021":3.2,"unemployment_rate_2022":4.8}
